{
  "Level": [
    [
      "Wall",
      "Wall",
      "Wall",
      "Wall",
      "Path",
      "Wall",
      "Path",
      "Wall",
      "Path",
      "Path",
      "Path",
      "Path",
      "Path",
      "Path",
      "Path"
    ],
    [
      "Path",
      "Path",
      "Path",
      "Path",
      "Wall",
      "Path",
      "Wall",
      "Wall",
      "Path",
      "Wall",
      "Wall",
      "Abyss",
      "Wall",
      "Wall",
      "Path"
    ],
    [
      "Path",
      "Abyss",
      "Abyss",
      "Path",
      "Path",
      "Path",
      "Path",
      "Path",
      "Path",
      "Path",
      "Path",
      "Path",
      "Path",
      "Wall",
      "Path"
    ],
    [
      "Path",
      "Path",
      "Wall",
      "Path",
      "Wall",
      "Start",
      "Wall",
      "Path",
      "LF-lr",
      "Path",
      "LF-t",
      "Path",
      "LF-t",
      "Path",
      "Path"
    ],
    [
      "Abyss",
      "Path",
      "Abyss",
      "Path",
      "Path",
      "Wall",
      "Wall",
      "Path",
      "LF-lr",
      "Path",
      "Wall",
      "Path",
      "Wall",
      "Path",
      "Abyss"
    ],
    [
      "Path",
      "Path",
      "Abyss",
      "Wall",
      "Path",
      "Path",
      "Wall",
      "Path",
      "LF-blr",
      "Path",
      "Wall",
      "Path",
      "Wall",
      "Path",
      "Path"
    ],
    [
      "Path",
      "Abyss",
      "Abyss",
      "Path",
      "LF-lr",
      "Path",
      "Wall",
      "Path",
      "Path",
      "Path",
      "Wall",
      "Wall",
      "Wall",
      "Abyss",
      "Path"
    ],
    [
      "Path",
      "Path",
      "Abyss",
      "Path",
      "LF-lr",
      "Path",
      "Wall",
      "Wall",
      "Wall",
      "Wall",
      "Wall",
      "Abyss",
      "Path",
      "Check",
      "Path"
    ],
    [
      "Abyss",
      "Path",
      "Abyss",
      "Air-l-1",
      "Air-l-1",
      "Air-l-1",
      "Airvent-l",
      "Path",
      "Path",
      "Path",
      "Goal",
      "Wall",
      "Abyss",
      "Wall",
      "Path"
    ],
    [
      "Path",
      "Path",
      "LF-bl",
      "Path",
      "LF-blrt",
      "Path",
      "Wall",
      "Path",
      "Wall",
      "Wall",
      "Wall",
      "Path",
      "Wall",
      "Wall",
      "Path"
    ],
    [
      "Abyss",
      "LF-rt",
      "Path",
      "Path",
      "Path",
      "Path",
      "Wall",
      "Path",
      "Path",
      "Wall",
      "Path",
      "Path",
      "Path",
      "Wall",
      "Path"
    ],
    [
      "Wall",
      "Path",
      "Path",
      "Wall",
      "Wall",
      "Wall",
      "Path",
      "Wall",
      "Path",
      "Wall",
      "Path",
      "Abyss",
      "Path",
      "Wall",
      "Path"
    ],
    [
      "Wall",
      "Path",
      "Wall",
      "Check",
      "Path",
      "Wall",
      "Path",
      "Path",
      "Path",
      "Wall",
      "Path",
      "Path",
      "Path",
      "Wall",
      "Path"
    ],
    [
      "Wall",
      "Path",
      "Wall",
      "Wall",
      "Path",
      "LF-l",
      "Wall",
      "Wall",
      "Path",
      "LF-lr",
      "Path",
      "Wall",
      "Wall",
      "Wall",
      "Path"
    ],
    [
      "Airvent-r",
      "Air-r-1",
      "Air-r-1",
      "Air-r-1",
      "Air-r-1",
      "Air-r-1",
      "Air-r-1",
      "Air-r-1",
      "Air-r-1",
      "Air-r-1",
      "Air-r-1",
      "Air-r-1",
      "Air-r-1",
      "Air-r-1",
      "Air-r-1"
    ]
  ],
  "Collectibles": {
    "Key": [
      {
        "x": 12.5,
        "y": 7.6
      }
    ],
    "Invert": [
      {
        "x": 0.5,
        "y": 9.5,
        "duration": 5000
      },
      {
        "x": 8.4,
        "y": 6.5,
        "duration": 10000
      }
    ],
    "Visibility": [
      {
        "x": 1.4,
        "y": 13.5,
        "duration": 10000,
        "difference": -1
      }
    ],
    "Life": [
      {
        "x": 12.3,
        "y": 2.4
      },
      {
        "x": 5.4,
        "y": 10.5
      },
      {
        "x": 3.4,
        "y": 6.5
      }
    ]
  },
  "Traps": {},
  "Monster": {
    "Patroler": [
      [
        {
          "x": 6.4,
          "y": 2.3
        },
        {
          "x": 3.5,
          "y": 2.5
        },
        {
          "x": 3.4,
          "y": 4.5
        },
        {
          "x": 4.5,
          "y": 4.4
        },
        {
          "x": 4.4,
          "y": 5.5
        },
        {
          "x": 7.5,
          "y": 5.5
        },
        {
          "x": 7.4,
          "y": 2.5
        },
        {
          "x": 7.4,
          "y": 2.5
        }
      ],
      [
        {
          "x": 11.4,
          "y": 0.5
        },
        {
          "x": 11.4,
          "y": 5.4
        },
        {
          "x": 14.3,
          "y": 5.6
        }
      ]
    ]
  }
}